salmanmodule/__init__.py
salmanmodule/cmodule.py
salmanmodule/salmanmath/__init__.py
salmanmodule/salmanmath/salmanagetosec/__init__.py
salmanmodule/salmanmath/salmanagetosec/sagetosec.py
salmanmodule/salmanmath/salmancalculator/__init__.py
salmanmodule/salmanmath/salmancalculator/scal.py
salmanmodule/salmanmath/salmanfibo/__init__.py
salmanmodule/salmanmath/salmanfibo/sfibo.py
salmanmodule/salmanmath/salmangeometry/__init__.py
salmanmodule/salmanmath/salmangeometry/sgeo.py
salmanmodule/salmanmath/salmanprime/__init__.py
salmanmodule/salmanmath/salmanprime/sprime.py
salmanmodule/salmanmath/salmansorting/__init__.py
salmanmodule/salmanmath/salmansorting/ssort.py
salmanmodule/simplecode/__init__.py
salmanmodule/simplecode/simpleintro.py
salmanmodule-0.1.dist-info/LICENSE.txt
salmanmodule-0.1.dist-info/METADATA
salmanmodule-0.1.dist-info/WHEEL
salmanmodule-0.1.dist-info/top_level.txt
salmanmodule-0.1.dist-info/RECORD
