Metadata-Version: 2.1
Name: salmanmodule
Version: 0.1
Summary: It is my Module for Public Use
Author: Salman Mumtaz
Author-email: msdsf22m007@pucit.edu.pk
Classifier: Operating System :: Microsoft :: Windows :: Windows 10
Classifier: License :: OSI Approved :: MIT License
Classifier: Programming Language :: Python :: 3
License-File: LICENSE.txt
